digit_bin_index-0.4.2.dist-info/METADATA
digit_bin_index-0.4.2.dist-info/WHEEL
digit_bin_index-0.4.2.dist-info/licenses/LICENSE
digit_bin_index/__init__.py
digit_bin_index/digit_bin_index.abi3.so
digit_bin_index-0.4.2.dist-info/RECORD
