Metadata-Version: 2.4
Name: digit-bin-index
Version: 0.4.2
Classifier: Programming Language :: Rust
Classifier: Programming Language :: Python :: Implementation :: CPython
Classifier: Programming Language :: Python :: 3
Classifier: Programming Language :: Python :: 3.8
Classifier: Programming Language :: Python :: 3.9
Classifier: Programming Language :: Python :: 3.10
Classifier: Programming Language :: Python :: 3.11
Classifier: Programming Language :: Python :: 3.12
License-File: LICENSE
Summary: A high-performance, O(P) data structure for weighted random sampling of binned probabilities, ideal for large-scale simulations.
Author: Lars Rönnbäck <lars.ronnback@anchormodeling.com>
Author-email: Lars Rönnbäck <lars.ronnback@anchormodeling.com>
License: MIT
Requires-Python: >=3.8
